{"win_model_info": {"features": ["age", "num_previous_seasons", "vote_accuracy_by_previous_ep", "times_in_danger", "final_n", "has_advantage", "confessional_share_rolling_3"], "coefficients": [-0.2734813467651157, 0.1877738566969995, -0.031967410146717494, -0.39426626131999903, -0.38631915175055404, 0.03205767633885346, 0.382471855294255], "intercept": -0.18608418055145862, "scaler_means": [33.20075046904315, 0.25623157330474405, 0.5773576117887295, 0.45658000536049315, 13.171401768962745, 0.14419726614848566, 0.06316443598214588], "scaler_stds": [9.813493108183783, 0.6055321251832672, 0.43435455455130956, 0.8303922664824285, 4.151153994702849, 0.3512896448570445, 0.05244539151593793]}, "elim_model_info": {"features": ["age", "num_previous_seasons", "votes_against_last_3_eps", "advantages_held", "individual_immunity_rate", "team_immunity_rate"], "coefficients": [0.017151675583324973, 0.013709706474388236, 0.25976085866484677, -0.16747209884903977, 0.1974843849224366, 0.0003758270150654608], "intercept": -2.237146903915168, "scaler_means": [33.20075046904315, 0.25623157330474405, 0.5414098097024926, 0.16483516483516483, 0.035001148677106866, 0.5144157381526719], "scaler_stds": [9.813493108183783, 0.6055321251832672, 1.328445988418016, 0.4345770852198997, 0.13980233063797337, 0.34679874252607207]}, "players": [{"season": 13, "castaway_id": "US0183", "castaway": "Sekou", "won_season": 0, "episode": [1], "prob_win": [0.03733265686406329], "prob_eliminated": [0.05105963441582034], "eliminated_this_episode": [1], "win_features": {"age": [45], "num_previous_seasons": [0], "vote_accuracy_by_previous_ep": [0.0], "times_in_danger": [0], "final_n": [20.0], "has_advantage": [0], "confessional_share_rolling_3": [0.0]}, "elim_features": {"age": [45], "num_previous_seasons": [0], "votes_against_last_3_eps": [0], "advantages_held": [0], "individual_immunity_rate": [0.0], "team_immunity_rate": [0.0]}}, {"season": 13, "castaway_id": "US0184", "castaway": "Billy", "won_season": 0, "episode": [1, 2], "prob_win": [0.04549934349188362, 0.04721730111284992], "prob_eliminated": [0.05033338867018533, 0.05272426458519794], "eliminated_this_episode": [0, 1], "win_features": {"age": [36, 36], "num_previous_seasons": [0, 0], "vote_accuracy_by_previous_ep": [0.0, 0.0], "times_in_danger": [0, 0], "final_n": [20.0, 19.0], "has_advantage": [0, 0], "confessional_share_rolling_3": [0.0, 0.0425531914893617]}, "elim_features": {"age": [36, 36], "num_previous_seasons": [0, 0], "votes_against_last_3_eps": [0, 0], "advantages_held": [0, 0], "individual_immunity_rate": [0.0, 0.0], "team_immunity_rate": [0.0, 1.0]}}, {"season": 13, "castaway_id": "US0185", "castaway": "Cecilia", "won_season": 0, "episode": [1, 2, 3], "prob_win": [0.05266130232946891, 0.04852316984809754, 0.053462426953063295], "prob_eliminated": [0.049774991494956636, 0.052139398687392986, 0.05443863894569466], "eliminated_this_episode": [0, 0, 1], "win_features": {"age": [29, 29, 29], "num_previous_seasons": [0, 0, 0], "vote_accuracy_by_previous_ep": [0.0, 0.0, 1.0], "times_in_danger": [0, 0, 0], "final_n": [20.0, 19.0, 18.0], "has_advantage": [0, 0, 0], "confessional_share_rolling_3": [0.0, 0.02127659574468085, 0.03502854177477945]}, "elim_features": {"age": [29, 29, 29], "num_previous_seasons": [0, 0, 0], "votes_against_last_3_eps": [0, 0, 0], "advantages_held": [0, 0, 0], "individual_immunity_rate": [0.0, 0.0, 0.0], "team_immunity_rate": [0.0, 1.0, 0.5]}}, {"season": 13, "castaway_id": "US0186", "castaway": "J.P.", "won_season": 0, "episode": [1, 2, 3, 4], "prob_win": [0.05159578644253332, 0.052810762973744825, 0.05520986299201735, 0.05888522610592425], "prob_eliminated": [0.049854418307843276, 0.05222259050635319, 0.0545255034879666, 0.055507452350959906], "eliminated_this_episode": [0, 0, 0, 1], "win_features": {"age": [30, 30, 30, 30], "num_previous_seasons": [0, 0, 0, 0], "vote_accuracy_by_previous_ep": [0.0, 0.0, 1.0, 1.0], "times_in_danger": [0, 0, 0, 0], "final_n": [20.0, 19.0, 18.0, 17.0], "has_advantage": [0, 0, 0, 0], "confessional_share_rolling_3": [0.0, 0.0425531914893617, 0.04566683964711987, 0.04493731338793499]}, "elim_features": {"age": [30, 30, 30, 30], "num_previous_seasons": [0, 0, 0, 0], "votes_against_last_3_eps": [0, 0, 0, 0], "advantages_held": [0, 0, 0, 0], "individual_immunity_rate": [0.0, 0.0, 0.0, 0.0], "team_immunity_rate": [0.0, 1.0, 0.5, 0.6666666666666666]}}, {"season": 13, "castaway_id": "US0187", "castaway": "Stephannie", "won_season": 0, "episode": [1, 2, 3, 4, 5], "prob_win": [0.046479597926717235, 0.06752805927568825, 0.05814727416606331, 0.05918736974856101, 0.04836714009710024], "prob_eliminated": [0.05025327280219139, 0.05258838118412535, 0.05496170753557124, 0.05595150488803769, 0.08400783131033528], "eliminated_this_episode": [0, 0, 0, 0, 1], "win_features": {"age": [35, 35, 35, 35, 35], "num_previous_seasons": [0, 0, 0, 0, 0], "vote_accuracy_by_previous_ep": [0.0, 1.0, 1.0, 1.0, 1.0], "times_in_danger": [0, 0, 0, 0, 1], "final_n": [20.0, 19.0, 18.0, 17.0, 16.0], "has_advantage": [0, 0, 0, 0, 0], "confessional_share_rolling_3": [0.0, 0.1276595744680851, 0.07602490918526206, 0.0651760264133631, 0.07024188254304903]}, "elim_features": {"age": [35, 35, 35, 35, 35], "num_previous_seasons": [0, 0, 0, 0, 0], "votes_against_last_3_eps": [0, 0, 0, 0, 2], "advantages_held": [0, 0, 0, 0, 0], "individual_immunity_rate": [0.0, 0.0, 0.0, 0.0, 0.0], "team_immunity_rate": [0.0, 0.0, 0.5, 0.6666666666666666, 0.5]}}, {"season": 13, "castaway_id": "US0188", "castaway": "Cao Boi", "won_season": 0, "episode": [1, 2, 3, 4, 5, 6], "prob_win": [0.0399235277629499, 0.0574007760004799, 0.05422010168662103, 0.0562210405965346, 0.06009651549698014, 0.06328992395149453], "prob_eliminated": [0.05081650926286943, 0.053230284690331114, 0.05560511079042683, 0.05657856632686989, 0.059902959634269975, 0.06538911791554718], "eliminated_this_episode": [0, 0, 0, 0, 0, 1], "win_features": {"age": [42, 42, 42, 42, 42, 42], "num_previous_seasons": [0, 0, 0, 0, 0, 0], "vote_accuracy_by_previous_ep": [0.0, 0.0, 0.0, 1.0, 1.0, 1.0], "times_in_danger": [0, 0, 0, 0, 0, 0], "final_n": [20.0, 19.0, 18.0, 17.0, 16.0, 15.0], "has_advantage": [0, 0, 0, 0, 0, 0], "confessional_share_rolling_3": [0.0, 0.10638297872340426, 0.07758173326414115, 0.08070666275580425, 0.07699170159403457, 0.07588305414392371]}, "elim_features": {"age": [42, 42, 42, 42, 42, 42], "num_previous_seasons": [0, 0, 0, 0, 0, 0], "votes_against_last_3_eps": [0, 0, 0, 0, 0, 0], "advantages_held": [0, 0, 0, 0, 0, 0], "individual_immunity_rate": [0.0, 0.0, 0.0, 0.0, 0.0, 0.0], "team_immunity_rate": [0.0, 1.0, 1.0, 0.6666666666666666, 0.75, 0.8]}}, {"season": 13, "castaway_id": "US0189", "castaway": "Cristina", "won_season": 0, "episode": [1, 2, 3, 4, 5, 6], "prob_win": [0.046479597926717235, 0.038560004255410896, 0.05739619053464892, 0.05487403043573605, 0.05969808539495584, 0.03548703438485753], "prob_eliminated": [0.05025327280219139, 0.05264035120176099, 0.05496170753557124, 0.05595150488803769, 0.0592244327692146, 0.07712399815799972], "eliminated_this_episode": [0, 0, 0, 0, 0, 1], "win_features": {"age": [35, 35, 35, 35, 35, 35], "num_previous_seasons": [0, 0, 0, 0, 0, 0], "vote_accuracy_by_previous_ep": [0.0, 0.0, 1.0, 1.0, 1.0, 1.0], "times_in_danger": [0, 0, 0, 0, 0, 1], "final_n": [20.0, 19.0, 18.0, 17.0, 16.0, 15.0], "has_advantage": [0, 0, 0, 0, 0, 0], "confessional_share_rolling_3": [0.0, 0.0, 0.07317073170731707, 0.048780487804878044, 0.048780487804878044, 0.0]}, "elim_features": {"age": [35, 35, 35, 35, 35, 35], "num_previous_seasons": [0, 0, 0, 0, 0, 0], "votes_against_last_3_eps": [0, 0, 0, 0, 0, 1], "advantages_held": [0, 0, 0, 0, 0, 0], "individual_immunity_rate": [0.0, 0.0, 0.0, 0.0, 0.0, 0.0], "team_immunity_rate": [0.0, 1.0, 0.5, 0.6666666666666666, 0.5, 0.4]}}, {"season": 13, "castaway_id": "US0190", "castaway": "Jessica", "won_season": 0, "episode": [1, 2, 3, 4, 5, 6, 8], "prob_win": [0.05483355294043784, 0.05571957085783465, 0.05764924772352169, 0.06771226887711865, 0.07358244101929873, 0.07489983225299238, 0.08023874758006613], "prob_eliminated": [0.04961648094609546, 0.05197337431356541, 0.05429212437376035, 0.055242551801331884, 0.0584884559192807, 0.06384507547516619, 0.07372466893037229], "eliminated_this_episode": [0, 0, 0, 0, 0, 0, 1], "win_features": {"age": [27, 27, 27, 27, 27, 27, 27], "num_previous_seasons": [0, 0, 0, 0, 0, 0, 0], "vote_accuracy_by_previous_ep": [0.0, 0.0, 0.0, 1.0, 1.0, 1.0, 0.5], "times_in_danger": [0, 0, 0, 0, 0, 0, 0], "final_n": [20.0, 19.0, 18.0, 17.0, 16.0, 15.0, 13.0], "has_advantage": [0, 0, 0, 0, 0, 0, 0], "confessional_share_rolling_3": [0.0, 0.0425531914893617, 0.03347171769590036, 0.06579273933349879, 0.0674813580433941, 0.05935127674258109, 0.027777777777777776]}, "elim_features": {"age": [27, 27, 27, 27, 27, 27, 27], "num_previous_seasons": [0, 0, 0, 0, 0, 0, 0], "votes_against_last_3_eps": [0, 0, 0, 0, 0, 0, 0], "advantages_held": [0, 0, 0, 0, 0, 0, 0], "individual_immunity_rate": [0.0, 0.0, 0.0, 0.0, 0.0, 0.0, 0.0], "team_immunity_rate": [0.0, 1.0, 1.0, 0.6666666666666666, 0.75, 0.8, 0.8]}}, {"season": 13, "castaway_id": "US0191", "castaway": "Brad", "won_season": 0, "episode": [1, 2, 3, 4, 5, 6, 8, 9], "prob_win": [0.05266130232946891, 0.04852316984809754, 0.04988447205413502, 0.06417857228009652, 0.06456650700841307, 0.06814896821422241, 0.07247084263790617, 0.0878492071636065], "prob_eliminated": [0.049774991494956636, 0.052139398687392986, 0.054465555790749756, 0.05543729094478357, 0.058675296589159646, 0.06403636369834884, 0.07394555771183993, 0.0783968671751773], "eliminated_this_episode": [0, 0, 0, 0, 0, 0, 0, 1], "win_features": {"age": [29, 29, 29, 29, 29, 29, 29, 29], "num_previous_seasons": [0, 0, 0, 0, 0, 0, 0, 0], "vote_accuracy_by_previous_ep": [0.0, 0.0, 0.0, 0.0, 1.0, 1.0, 0.6666666666666666, 0.6666666666666666], "times_in_danger": [0, 0, 0, 0, 0, 0, 0, 0], "final_n": [20.0, 19.0, 18.0, 17.0, 16.0, 15.0, 13.0, 12.0], "has_advantage": [0, 0, 0, 0, 0, 0, 0, 0], "confessional_share_rolling_3": [0.0, 0.02127659574468085, 0.010638297872340425, 0.0505704594511255, 0.043478260869565216, 0.043478260869565216, 0.011904761904761904, 0.04089026915113871]}, "elim_features": {"age": [29, 29, 29, 29, 29, 29, 29, 29], "num_previous_seasons": [0, 0, 0, 0, 0, 0, 0, 0], "votes_against_last_3_eps": [0, 0, 0, 0, 0, 0, 0, 0], "advantages_held": [0, 0, 0, 0, 0, 0, 0, 0], "individual_immunity_rate": [0.0, 0.0, 0.0, 0.0, 0.0, 0.0, 0.0, 0.0], "team_immunity_rate": [0.0, 1.0, 1.0, 1.0, 0.75, 0.6, 0.6, 0.6666666666666666]}}, {"season": 13, "castaway_id": "US0192", "castaway": "Rebecca", "won_season": 0, "episode": [1, 2, 3, 4, 5, 6, 8, 9, 10], "prob_win": [0.047474291487787576, 0.05178753551562517, 0.050940871860964375, 0.050919368741417774, 0.054112530754738354, 0.055309997755369406, 0.07046770908057515, 0.07152478469487597, 0.07975504420394704], "prob_eliminated": [0.050173272092143464, 0.05250466309771213, 0.05487421542150701, 0.055862438563468515, 0.059130154933616424, 0.06453597658214787, 0.07452248230903552, 0.07901111887815818, 0.08383070638603324], "eliminated_this_episode": [0, 0, 0, 0, 0, 0, 0, 0, 1], "win_features": {"age": [34, 34, 34, 34, 34, 34, 34, 34, 34], "num_previous_seasons": [0, 0, 0, 0, 0, 0, 0, 0, 0], "vote_accuracy_by_previous_ep": [0.0, 1.0, 1.0, 1.0, 1.0, 1.0, 1.0, 1.0, 1.0], "times_in_danger": [0, 0, 0, 0, 0, 0, 0, 0, 0], "final_n": [20.0, 19.0, 18.0, 17.0, 16.0, 15.0, 13.0, 12.0, 11.0], "has_advantage": [0, 0, 0, 0, 0, 0, 0, 0, 0], "confessional_share_rolling_3": [0.0, 0.06382978723404255, 0.04411001556824079, 0.02940667704549386, 0.02400309717382888, 0.015873015873015872, 0.027777777777777776, 0.011904761904761904, 0.011904761904761904]}, "elim_features": {"age": [34, 34, 34, 34, 34, 34, 34, 34, 34], "num_previous_seasons": [0, 0, 0, 0, 0, 0, 0, 0, 0], "votes_against_last_3_eps": [0, 0, 0, 0, 0, 0, 0, 0, 0], "advantages_held": [0, 0, 0, 0, 0, 0, 0, 0, 0], "individual_immunity_rate": [0.0, 0.0, 0.0, 0.0, 0.0, 0.0, 0.0, 0.0, 0.0], "team_immunity_rate": [0.0, 0.0, 0.5, 0.6666666666666666, 0.5, 0.4, 0.4, 0.5, 0.42857142857142855]}}, {"season": 13, "castaway_id": "US0193", "castaway": "Jenny", "won_season": 0, "episode": [1, 2, 3, 4, 5, 6, 8, 9, 10], "prob_win": [0.04549934349188362, 0.042329914729974105, 0.04930624463649189, 0.05002369424187988, 0.05423960264400964, 0.06993149182763224, 0.06332542180782699, 0.06421468551285815, 0.05360346913719209], "prob_eliminated": [0.05033338867018533, 0.05272426458519794, 0.055076515007559924, 0.05605915045518362, 0.05933349376239112, 0.06475470964153623, 0.1060585686231157, 0.11244267936754615, 0.11929920804267527], "eliminated_this_episode": [0, 0, 0, 0, 0, 0, 0, 0, 1], "win_features": {"age": [36, 36, 36, 36, 36, 36, 36, 36, 36], "num_previous_seasons": [0, 0, 0, 0, 0, 0, 0, 0, 0], "vote_accuracy_by_previous_ep": [0.0, 0.0, 0.0, 0.0, 1.0, 1.0, 1.0, 1.0, 1.0], "times_in_danger": [0, 0, 0, 0, 0, 0, 1, 1, 1], "final_n": [20.0, 19.0, 18.0, 17.0, 16.0, 15.0, 13.0, 12.0, 11.0], "has_advantage": [0, 0, 0, 0, 0, 0, 0, 0, 0], "confessional_share_rolling_3": [0.0, 0.02127659574468085, 0.03502854177477945, 0.0233523611831863, 0.03213317847464189, 0.07647907647907648, 0.07647907647907648, 0.06060606060606061, 0.0]}, "elim_features": {"age": [36, 36, 36, 36, 36, 36, 36, 36, 36], "num_previous_seasons": [0, 0, 0, 0, 0, 0, 0, 0, 0], "votes_against_last_3_eps": [0, 0, 0, 0, 0, 0, 2, 2, 2], "advantages_held": [0, 0, 0, 0, 0, 0, 0, 0, 0], "individual_immunity_rate": [0.0, 0.0, 0.0, 0.0, 0.0, 0.0, 0.0, 0.0, 0.0], "team_immunity_rate": [0.0, 1.0, 1.0, 1.0, 0.75, 0.6, 0.6, 0.6666666666666666, 0.5714285714285714]}}, {"season": 13, "castaway_id": "US0194", "castaway": "Nate", "won_season": 0, "episode": [1, 2, 3, 4, 5, 6, 8, 9, 10, 11], "prob_win": [0.055939957623081196, 0.05131890408916746, 0.06233876437567611, 0.0741949230293047, 0.08691887172413679, 0.09127392308000239, 0.10352652267015428, 0.12208537482873288, 0.14663921447594197, 0.1563145641503104], "prob_eliminated": [0.04953739695791586, 0.05183924088579184, 0.054178795371455285, 0.05515450593819476, 0.05838079943053282, 0.06371810545292535, 0.07357805115626645, 0.07800981223854915, 0.08276831401421121, 0.09910854231207547], "eliminated_this_episode": [0, 0, 0, 0, 0, 0, 0, 0, 0, 1], "win_features": {"age": [26, 26, 26, 26, 26, 26, 26, 26, 26, 26], "num_previous_seasons": [0, 0, 0, 0, 0, 0, 0, 0, 0, 0], "vote_accuracy_by_previous_ep": [0.0, 0.0, 0.0, 0.0, 0.0, 0.3333333333333333, 0.3333333333333333, 0.3333333333333333, 0.5, 0.6], "times_in_danger": [0, 0, 0, 0, 0, 0, 0, 0, 0, 0], "final_n": [20.0, 19.0, 18.0, 17.0, 16.0, 15.0, 13.0, 12.0, 11.0, 9.0], "has_advantage": [0, 0, 0, 0, 0, 0, 0, 0, 0, 0], "confessional_share_rolling_3": [0.0, 0.02127659574468085, 0.04722366372599896, 0.07496070335356453, 0.09961453651803598, 0.10552732291862725, 0.09776334776334776, 0.13848108413325805, 0.1958973520758418, 0.17605608223457195]}, "elim_features": {"age": [26, 26, 26, 26, 26, 26, 26, 26, 26, 26], "num_previous_seasons": [0, 0, 0, 0, 0, 0, 0, 0, 0, 0], "votes_against_last_3_eps": [0, 0, 0, 0, 0, 0, 0, 0, 0, 0], "advantages_held": [0, 0, 0, 0, 0, 0, 0, 0, 0, 0], "individual_immunity_rate": [0.0, 0.0, 0.0, 0.0, 0.0, 0.0, 0.0, 0.0, 0.0, 0.0], "team_immunity_rate": [0.0, 0.0, 0.5, 0.6666666666666666, 0.5, 0.4, 0.4, 0.5, 0.42857142857142855, 0.375]}}, {"season": 13, "castaway_id": "US0195", "castaway": "Candice", "won_season": 0, "episode": [1, 2, 3, 4, 5, 6, 8, 9, 10, 11, 12], "prob_win": [0.05933799721743977, 0.059697193288855574, 0.058464003191508296, 0.06051682348953837, 0.06608776146726145, 0.07404725646762732, 0.06455902107515667, 0.07437978628841573, 0.09548271348850955, 0.13166162080470173, 0.14293401503245898], "prob_eliminated": [0.04930082862546604, 0.05164275892740393, 0.053946758849538985, 0.054891129344928756, 0.05811638774149818, 0.06343893363597074, 0.08743560666991103, 0.09268086471278734, 0.09833213325590526, 0.09864746284343122, 0.08506975440933046], "eliminated_this_episode": [0, 0, 0, 0, 0, 0, 0, 0, 0, 0, 1], "win_features": {"age": [23, 23, 23, 23, 23, 23, 23, 23, 23, 23, 23], "num_previous_seasons": [0, 0, 0, 0, 0, 0, 0, 0, 0, 0, 0], "vote_accuracy_by_previous_ep": [0.0, 0.0, 0.0, 0.0, 0.0, 0.0, 1.0, 1.0, 1.0, 1.0, 0.8], "times_in_danger": [0, 0, 0, 0, 0, 0, 1, 1, 1, 1, 1], "final_n": [20.0, 19.0, 18.0, 17.0, 16.0, 15.0, 13.0, 12.0, 11.0, 9.0, 8.0], "has_advantage": [0, 0, 0, 0, 0, 0, 0, 0, 0, 0, 0], "confessional_share_rolling_3": [0.0, 0.0425531914893617, 0.02127659574468085, 0.014184397163120567, 0.015873015873015872, 0.031024531024531024, 0.031024531024531024, 0.04413702239789197, 0.08161708619374523, 0.1451091496858087, 0.1161236424394319]}, "elim_features": {"age": [23, 23, 23, 23, 23, 23, 23, 23, 23, 23, 23], "num_previous_seasons": [0, 0, 0, 0, 0, 0, 0, 0, 0, 0, 0], "votes_against_last_3_eps": [0, 0, 0, 0, 0, 0, 1, 1, 1, 0, 0], "advantages_held": [0, 0, 0, 0, 0, 0, 0, 0, 0, 0, 0], "individual_immunity_rate": [0.0, 0.0, 0.0, 0.0, 0.0, 0.0, 0.0, 0.0, 0.0, 0.0, 0.0], "team_immunity_rate": [0.0, 1.0, 1.0, 0.6666666666666666, 0.75, 0.8, 0.8, 0.6666666666666666, 0.5714285714285714, 0.5, 0.5]}}, {"season": 13, "castaway_id": "US0196", "castaway": "Jonathan", "won_season": 0, "episode": [1, 2, 3, 4, 5, 6, 8, 9, 10, 11, 12, 13], "prob_win": [0.038181723124129006, 0.05542921912498853, 0.05539164778379502, 0.06814705599535141, 0.06793162541974866, 0.0732610325624639, 0.05951915278955791, 0.04663573008778516, 0.046034920422980526, 0.04266394540913599, 0.09370377795199866, 0.08955938547461251], "prob_eliminated": [0.050978476446178575, 0.05339992877386855, 0.05578232340754726, 0.05675888718385481, 0.0600938740756458, 0.06559751606855721, 0.09035407653900862, 0.11382428876675468, 0.14291584344497446, 0.2360062001455722, 0.17378976858772055, 0.25338670401165475], "eliminated_this_episode": [0, 0, 0, 0, 0, 0, 0, 0, 0, 0, 0, 1], "win_features": {"age": [44, 44, 44, 44, 44, 44, 44, 44, 44, 44, 44, 44], "num_previous_seasons": [0, 0, 0, 0, 0, 0, 0, 0, 0, 0, 0, 0], "vote_accuracy_by_previous_ep": [0.0, 0.0, 0.0, 1.0, 1.0, 1.0, 1.0, 1.0, 1.0, 1.0, 1.0, 1.0], "times_in_danger": [0, 0, 0, 0, 0, 0, 1, 2, 3, 4, 4, 5], "final_n": [20.0, 19.0, 18.0, 17.0, 16.0, 15.0, 13.0, 12.0, 11.0, 9.0, 8.0, 7.0], "has_advantage": [0, 0, 0, 0, 0, 0, 0, 0, 0, 0, 0, 0], "confessional_share_rolling_3": [0.0, 0.10638297872340426, 0.08977685521536066, 0.13231500492618245, 0.11272702789139692, 0.11863981429198821, 0.0937950937950938, 0.09241483154526632, 0.13228723983872726, 0.1481602557117431, 0.2690841687552214, 0.287797619047619]}, "elim_features": {"age": [44, 44, 44, 44, 44, 44, 44, 44, 44, 44, 44, 44], "num_previous_seasons": [0, 0, 0, 0, 0, 0, 0, 0, 0, 0, 0, 0], "votes_against_last_3_eps": [0, 0, 0, 0, 0, 0, 1, 2, 3, 5, 4, 6], "advantages_held": [0, 0, 0, 0, 0, 0, 0, 0, 0, 0, 0, 0], "individual_immunity_rate": [0.0, 0.0, 0.0, 0.0, 0.0, 0.0, 0.0, 0.0, 0.0, 0.0, 0.0, 0.0], "team_immunity_rate": [0.0, 1.0, 1.0, 0.6666666666666666, 0.75, 0.8, 0.8, 0.6666666666666666, 0.5714285714285714, 0.5, 0.5, 0.5]}}, {"season": 13, "castaway_id": "US0197", "castaway": "Parvati", "won_season": 0, "episode": [1, 2, 3, 4, 5, 6, 8, 9, 10, 11, 12, 13, 14], "prob_win": [0.05933799721743977, 0.059697193288855574, 0.058464003191508296, 0.06848029244289672, 0.08525625670210563, 0.0974333318151071, 0.10375554113164882, 0.09073088798000788, 0.08988417338066636, 0.10428898647679034, 0.12723501586674624, 0.18196700184978393, 0.20856920265549794], "prob_eliminated": [0.04930082862546604, 0.05164275892740393, 0.053946758849538985, 0.05490923800281671, 0.05811638774149818, 0.06342637963747141, 0.07324118274468239, 0.07765009555195797, 0.0823847113962239, 0.09864746284343122, 0.08506975440933046, 0.0910105154226149, 0.11710477453782774], "eliminated_this_episode": [0, 0, 0, 0, 0, 0, 0, 0, 0, 0, 0, 0, 1], "win_features": {"age": [23, 23, 23, 23, 23, 23, 23, 23, 23, 23, 23, 23, 23], "num_previous_seasons": [0, 0, 0, 0, 0, 0, 0, 0, 0, 0, 0, 0, 0], "vote_accuracy_by_previous_ep": [0.0, 0.0, 0.0, 0.0, 1.0, 1.0, 1.0, 1.0, 1.0, 1.0, 0.8333333333333334, 0.7142857142857143, 0.75], "times_in_danger": [0, 0, 0, 0, 0, 0, 0, 0, 0, 0, 0, 0, 0], "final_n": [20.0, 19.0, 18.0, 17.0, 16.0, 15.0, 13.0, 12.0, 11.0, 9.0, 8.0, 7.0, 6.0], "has_advantage": [0, 0, 0, 0, 0, 0, 0, 0, 0, 0, 0, 0, 0], "confessional_share_rolling_3": [0.0, 0.0425531914893617, 0.02127659574468085, 0.04316990440949738, 0.0924775707384403, 0.1227806010414706, 0.0937950937950938, 0.030303030303030304, 0.0, 0.0, 0.010416666666666666, 0.09930555555555555, 0.15486111111111112]}, "elim_features": {"age": [23, 23, 23, 23, 23, 23, 23, 23, 23, 23, 23, 23, 23], "num_previous_seasons": [0, 0, 0, 0, 0, 0, 0, 0, 0, 0, 0, 0, 0], "votes_against_last_3_eps": [0, 0, 0, 0, 0, 0, 0, 0, 0, 0, 0, 0, 0], "advantages_held": [0, 0, 0, 0, 0, 0, 0, 0, 0, 0, 0, 0, 0], "individual_immunity_rate": [0.0, 0.0, 0.0, 0.0, 0.0, 0.0, 0.0, 0.0, 0.0, 0.0, 0.0, 0.0, 0.0], "team_immunity_rate": [0.0, 1.0, 1.0, 1.0, 0.75, 0.6, 0.6, 0.6666666666666666, 0.5714285714285714, 0.5, 0.5, 0.5, 0.5]}}, {"season": 13, "castaway_id": "US0198", "castaway": "Adam", "won_season": 0, "episode": [1, 2, 3, 4, 5, 6, 8, 9, 10, 11, 12, 13, 14, 15], "prob_win": [0.05374061038104934, 0.05474237926817008, 0.05350345420460356, 0.05545635443082904, 0.05383274785827573, 0.06980166793308368, 0.09040864730027902, 0.10615361533047986, 0.11289786201873658, 0.12542825726795803, 0.15092320858361896, 0.16780537109863514, 0.15575374148111334, 0.2018024188819928], "prob_eliminated": [0.0496956790830773, 0.052056326667123384, 0.054378777579482465, 0.05534896449927413, 0.05858180891536531, 0.06393433275432077, 0.07382773816956296, 0.07827195602626782, 0.08304449498520908, 0.09943749314293165, 0.08575104596632772, 0.1705771171878737, 0.2122518378974377, 0.2253508228666574], "eliminated_this_episode": [0, 0, 0, 0, 0, 0, 0, 0, 0, 0, 0, 0, 0, 1], "win_features": {"age": [28, 28, 28, 28, 28, 28, 28, 28, 28, 28, 28, 28, 28, 28], "num_previous_seasons": [0, 0, 0, 0, 0, 0, 0, 0, 0, 0, 0, 0, 0, 0], "vote_accuracy_by_previous_ep": [0.0, 0.0, 0.0, 0.0, 1.0, 1.0, 1.0, 1.0, 1.0, 1.0, 0.8333333333333334, 0.7142857142857143, 0.75, 0.6666666666666666], "times_in_danger": [0, 0, 0, 0, 0, 0, 0, 0, 0, 0, 0, 0, 1, 1], "final_n": [20.0, 19.0, 18.0, 17.0, 16.0, 15.0, 13.0, 12.0, 11.0, 9.0, 8.0, 7.0, 6.0, 5.0], "has_advantage": [0, 0, 0, 0, 0, 0, 0, 0, 0, 0, 0, 0, 0, 0], "confessional_share_rolling_3": [0.0, 0.0425531914893617, 0.02127659574468085, 0.014184397163120567, 0.0, 0.04545454545454545, 0.06926406926406926, 0.09824957651044608, 0.08788275035414624, 0.0799462424176383, 0.09262740183792816, 0.07976190476190476, 0.09166666666666667, 0.10952380952380952]}, "elim_features": {"age": [28, 28, 28, 28, 28, 28, 28, 28, 28, 28, 28, 28, 28, 28], "num_previous_seasons": [0, 0, 0, 0, 0, 0, 0, 0, 0, 0, 0, 0, 0, 0], "votes_against_last_3_eps": [0, 0, 0, 0, 0, 0, 0, 0, 0, 0, 0, 0, 1, 1], "advantages_held": [0, 0, 0, 0, 0, 0, 0, 0, 0, 0, 0, 0, 0, 0], "individual_immunity_rate": [0.0, 0.0, 0.0, 0.0, 0.0, 0.0, 0.0, 0.0, 0.0, 0.0, 0.0, 0.5, 0.3333333333333333, 0.25], "team_immunity_rate": [0.0, 1.0, 1.0, 1.0, 0.75, 0.6, 0.6, 0.6666666666666666, 0.5714285714285714, 0.5, 0.5, 0.5, 0.5, 0.5]}}, {"season": 13, "castaway_id": "US0199", "castaway": "Sundra", "won_season": 0, "episode": [1, 2, 3, 4, 5, 6, 8, 9, 10, 11, 12, 13, 14, 15], "prob_win": [0.05054420580226664, 0.039386709371340235, 0.038583578287119245, 0.03959939520615747, 0.038755117341317556, 0.04668923171192663, 0.06335567885385741, 0.07326054521671807, 0.08321675928224423, 0.09435490826508405, 0.11784127089532606, 0.13049368014097174, 0.16954278006820406, 0.17773949060739647], "prob_eliminated": [0.04993395964786117, 0.07414146673826326, 0.07748596590772605, 0.07885594857553607, 0.058848134109789195, 0.0642408672041732, 0.07418170675152375, 0.07863427594814142, 0.08344265457858108, 0.09992659739214362, 0.08617283054305892, 0.09219062377226357, 0.11862323997639919, 0.19750123202018213], "eliminated_this_episode": [0, 0, 0, 0, 0, 0, 0, 0, 0, 0, 0, 0, 0, 0], "win_features": {"age": [31, 31, 31, 31, 31, 31, 31, 31, 31, 31, 31, 31, 31, 31], "num_previous_seasons": [0, 0, 0, 0, 0, 0, 0, 0, 0, 0, 0, 0, 0, 0], "vote_accuracy_by_previous_ep": [0.0, 1.0, 1.0, 0.5, 0.5, 0.5, 0.6666666666666666, 0.75, 0.75, 0.75, 0.8, 0.8333333333333334, 0.8571428571428571, 0.875], "times_in_danger": [0, 1, 1, 1, 1, 1, 1, 1, 1, 1, 1, 1, 1, 2], "final_n": [20.0, 19.0, 18.0, 17.0, 16.0, 15.0, 13.0, 12.0, 11.0, 9.0, 8.0, 7.0, 6.0, 5.0], "has_advantage": [0, 0, 0, 0, 0, 0, 0, 0, 0, 0, 0, 0, 0, 0], "confessional_share_rolling_3": [0.0, 0.06382978723404255, 0.04411001556824079, 0.02940667704549386, 0.008130081300813009, 0.030303030303030304, 0.05411255411255411, 0.06860530773574251, 0.07338999673095782, 0.06545348879444988, 0.08221073517126148, 0.06934523809523808, 0.13680555555555554, 0.14126984126984127]}, "elim_features": {"age": [31, 31, 31, 31, 31, 31, 31, 31, 31, 31, 31, 31, 31, 31], "num_previous_seasons": [0, 0, 0, 0, 0, 0, 0, 0, 0, 0, 0, 0, 0, 0], "votes_against_last_3_eps": [0, 2, 2, 2, 0, 0, 0, 0, 0, 0, 0, 0, 0, 2], "advantages_held": [0, 0, 0, 0, 0, 0, 0, 0, 0, 0, 0, 0, 0, 0], "individual_immunity_rate": [0.0, 0.0, 0.0, 0.0, 0.0, 0.0, 0.0, 0.0, 0.0, 0.0, 0.0, 0.0, 0.0, 0.0], "team_immunity_rate": [0.0, 0.0, 0.5, 0.3333333333333333, 0.5, 0.6, 0.6, 0.5, 0.5714285714285714, 0.625, 0.625, 0.625, 0.625, 0.625]}}, {"season": 13, "castaway_id": "US0200", "castaway": "Becky", "won_season": 0, "episode": [1, 2, 3, 4, 5, 6, 8, 9, 10, 11, 12, 13, 14, 15], "prob_win": [0.05374061038104934, 0.044426614235267635, 0.054298702383983294, 0.03816922880155554, 0.04562347689830843, 0.04478481065670494, 0.054860025722661625, 0.05966444307498058, 0.066952926899386, 0.08505008838505902, 0.09498525901937853, 0.12088970017517114, 0.13588928292160807, 0.18190231892274508], "prob_eliminated": [0.0496956790830773, 0.052056326667123384, 0.054378777579482465, 0.09298160110677055, 0.09844441946758342, 0.10746002692100752, 0.07384233977602792, 0.07827195602626782, 0.08305622649680827, 0.09946207728651346, 0.08577224638037373, 0.09176206521617919, 0.11807180641014067, 0.1385534537162551], "eliminated_this_episode": [0, 0, 0, 0, 0, 0, 0, 0, 0, 0, 0, 0, 0, 0], "win_features": {"age": [28, 28, 28, 28, 28, 28, 28, 28, 28, 28, 28, 28, 28, 28], "num_previous_seasons": [0, 0, 0, 0, 0, 0, 0, 0, 0, 0, 0, 0, 0, 0], "vote_accuracy_by_previous_ep": [0.0, 0.0, 0.0, 1.0, 1.0, 1.0, 1.0, 1.0, 1.0, 1.0, 1.0, 1.0, 1.0, 1.0], "times_in_danger": [0, 0, 0, 1, 1, 1, 1, 1, 1, 1, 1, 1, 1, 1], "final_n": [20.0, 19.0, 18.0, 17.0, 16.0, 15.0, 13.0, 12.0, 11.0, 9.0, 8.0, 7.0, 6.0, 5.0], "has_advantage": [0, 0, 0, 0, 0, 0, 0, 0, 0, 0, 0, 0, 0, 0], "confessional_share_rolling_3": [0.0, 0.0, 0.024390243902439025, 0.016260162601626018, 0.03213317847464189, 0.015873015873015872, 0.015873015873015872, 0.014492753623188406, 0.014492753623188406, 0.030365769496204276, 0.015873015873015872, 0.03809523809523809, 0.049999999999999996, 0.07380952380952381]}, "elim_features": {"age": [28, 28, 28, 28, 28, 28, 28, 28, 28, 28, 28, 28, 28, 28], "num_previous_seasons": [0, 0, 0, 0, 0, 0, 0, 0, 0, 0, 0, 0, 0, 0], "votes_against_last_3_eps": [0, 0, 0, 3, 3, 3, 0, 0, 0, 0, 0, 0, 0, 0], "advantages_held": [0, 0, 0, 0, 0, 0, 0, 0, 0, 0, 0, 0, 0, 0], "individual_immunity_rate": [0.0, 0.0, 0.0, 0.0, 0.0, 0.0, 0.0, 0.0, 0.0, 0.0, 0.0, 0.0, 0.0, 0.0], "team_immunity_rate": [0.0, 1.0, 1.0, 0.6666666666666666, 0.75, 0.8, 0.8, 0.6666666666666666, 0.7142857142857143, 0.75, 0.75, 0.75, 0.75, 0.75]}}, {"season": 13, "castaway_id": "US0201", "castaway": "Ozzy", "won_season": 0, "episode": [1, 2, 3, 4, 5, 6, 8, 9, 10, 11, 12, 13, 14, 15], "prob_win": [0.05819238945736686, 0.06435375260279451, 0.06301686435586557, 0.061739539877261045, 0.06986694292977275, 0.06591644735149822, 0.0810967141994776, 0.09101461032679029, 0.10205479879425114, 0.1302706599898789, 0.14273729522622058, 0.14879345859914453, 0.16128591873111156, 0.21165132274174484], "prob_eliminated": [0.049379570923657884, 0.05172523393359878, 0.06445849628214333, 0.06559789947979237, 0.06945777434217755, 0.06352767725408685, 0.07335815548209129, 0.07776128486704048, 0.08251628752338336, 0.09881723383416986, 0.2754839233058026, 0.16960035080800487, 0.26478028547710725, 0.3411564625479271], "eliminated_this_episode": [0, 0, 0, 0, 0, 0, 0, 0, 0, 0, 0, 0, 0, 0], "win_features": {"age": [24, 24, 24, 24, 24, 24, 24, 24, 24, 24, 24, 24, 24, 24], "num_previous_seasons": [0, 0, 0, 0, 0, 0, 0, 0, 0, 0, 0, 0, 0, 0], "vote_accuracy_by_previous_ep": [0.0, 0.0, 1.0, 0.5, 0.5, 0.5, 0.6666666666666666, 0.75, 0.75, 0.75, 0.8, 0.8333333333333334, 0.8571428571428571, 0.875], "times_in_danger": [0, 0, 1, 1, 1, 1, 1, 1, 1, 1, 1, 1, 1, 1], "final_n": [20.0, 19.0, 18.0, 17.0, 16.0, 15.0, 13.0, 12.0, 11.0, 9.0, 8.0, 7.0, 6.0, 5.0], "has_advantage": [0, 0, 0, 0, 0, 0, 0, 0, 0, 0, 0, 0, 0, 0], "confessional_share_rolling_3": [0.0, 0.06382978723404255, 0.11728074727555787, 0.09267991847356032, 0.1031493544749112, 0.07654181567225045, 0.08585858585858586, 0.09759081498211931, 0.10237550397733464, 0.14205804365987432, 0.11941311612364243, 0.08432539682539682, 0.09027777777777778, 0.11706349206349205]}, "elim_features": {"age": [24, 24, 24, 24, 24, 24, 24, 24, 24, 24, 24, 24, 24, 24], "num_previous_seasons": [0, 0, 0, 0, 0, 0, 0, 0, 0, 0, 0, 0, 0, 0], "votes_against_last_3_eps": [0, 0, 1, 1, 1, 0, 0, 0, 0, 0, 0, 0, 0, 0], "advantages_held": [0, 0, 0, 0, 0, 0, 0, 0, 0, 0, 0, 0, 0, 0], "individual_immunity_rate": [0.0, 0.0, 0.0, 0.0, 0.0, 0.0, 0.0, 0.0, 0.0, 0.0, 1.0, 0.5, 0.6666666666666666, 0.75], "team_immunity_rate": [0.0, 1.0, 0.5, 0.3333333333333333, 0.5, 0.6, 0.6, 0.5, 0.5714285714285714, 0.625, 0.625, 0.625, 0.625, 0.625]}}, {"season": 13, "castaway_id": "US0202", "castaway": "Yul", "won_season": 1, "episode": [1, 2, 3, 4, 5, 6, 8, 9, 10, 11, 12, 13, 14, 15], "prob_win": [0.05054420580226664, 0.060547770312757564, 0.06972228961841372, 0.07169481569983702, 0.07106437724357695, 0.0697250500350173, 0.09241597515083227, 0.11248632949474886, 0.1234781178961445, 0.12996696925108156, 0.12964015742425197, 0.16049140266168105, 0.16895907414246497, 0.22690444884612077], "prob_eliminated": [0.04993395964786117, 0.03660898694039287, 0.03824226728427763, 0.03891136565015908, 0.041197789257641726, 0.0449709196007409, 0.05192986513656216, 0.055044800441351696, 0.05840941987599491, 0.06994693019973133, 0.12289067639805554, 0.131472623581409, 0.16916805570108742, 0.09743802884897823], "eliminated_this_episode": [0, 0, 0, 0, 0, 0, 0, 0, 0, 0, 0, 0, 0, 0], "win_features": {"age": [31, 31, 31, 31, 31, 31, 31, 31, 31, 31, 31, 31, 31, 31], "num_previous_seasons": [0, 0, 0, 0, 0, 0, 0, 0, 0, 0, 0, 0, 0, 0], "vote_accuracy_by_previous_ep": [0.0, 0.0, 0.0, 1.0, 1.0, 1.0, 1.0, 1.0, 1.0, 1.0, 1.0, 1.0, 1.0, 1.0], "times_in_danger": [0, 0, 0, 0, 0, 0, 0, 0, 0, 0, 1, 1, 1, 1], "final_n": [20.0, 19.0, 18.0, 17.0, 16.0, 15.0, 13.0, 12.0, 11.0, 9.0, 8.0, 7.0, 6.0, 5.0], "has_advantage": [0, 1, 1, 1, 1, 1, 1, 1, 1, 1, 1, 1, 1, 1], "confessional_share_rolling_3": [0.0, 0.06382978723404255, 0.08069538142189933, 0.0827824281943097, 0.06150583244962885, 0.04413702239789197, 0.07467532467532467, 0.1181535855448899, 0.12054593004249754, 0.09276815226471975, 0.10137322472848788, 0.1282738095238095, 0.12430555555555556, 0.16746031746031745]}, "elim_features": {"age": [31, 31, 31, 31, 31, 31, 31, 31, 31, 31, 31, 31, 31, 31], "num_previous_seasons": [0, 0, 0, 0, 0, 0, 0, 0, 0, 0, 0, 0, 0, 0], "votes_against_last_3_eps": [0, 0, 0, 0, 0, 0, 0, 0, 0, 0, 4, 4, 4, 0], "advantages_held": [0, 1, 1, 1, 1, 1, 1, 1, 1, 1, 1, 1, 1, 1], "individual_immunity_rate": [0.0, 0.0, 0.0, 0.0, 0.0, 0.0, 0.0, 0.0, 0.0, 0.0, 0.0, 0.0, 0.0, 0.0], "team_immunity_rate": [0.0, 1.0, 1.0, 0.6666666666666666, 0.75, 0.8, 0.8, 0.6666666666666666, 0.7142857142857143, 0.75, 0.75, 0.75, 0.75, 0.75]}}]}