{"win_model_info": {"features": ["age", "num_previous_seasons", "votes_against_last_3_eps", "times_in_danger", "final_n", "confessional_share_rolling_3", "elim_risk_rank"], "coefficients": [-0.32212786251335335, 0.13305514317361655, 0.01913819065630614, -0.3708426438508745, -0.4108492442761281, 0.36807236939428184, 0.0795246836466391], "intercept": -0.2004581195572918, "scaler_means": [33.288708459214504, 0.23923716012084592, 0.5492824773413897, 0.45902567975830816, 12.985271903323262, 0.06444895506782687, 6.987726586102719], "scaler_stds": [10.176311690932824, 0.5318209821435484, 1.3458800056813967, 0.8293962529187455, 4.124727657595277, 0.055224234296209776, 4.384548325184623]}, "elim_model_info": {"features": ["age", "mbti_feeling", "num_previous_seasons", "votes_against_last_3_eps", "advantages_held", "individual_immunity_wins"], "coefficients": [0.0382909911715047, -0.01028618198132653, -0.03962069656976238, 0.24631238789663565, -0.25607440759806643, 0.25605710150466365], "intercept": -2.285055766779822, "scaler_means": [33.288708459214504, 0.5264350453172205, 0.23923716012084592, 0.5492824773413897, 0.09384441087613293, 0.10876132930513595], "scaler_stds": [10.176311690932824, 0.49930069935768817, 0.5318209821435484, 1.3458800056813967, 0.31164439601645266, 0.40469149095950924]}, "players": [{"season": 36, "castaway_id": "US0517", "castaway": "Gonzalez", "won_season": 0, "episode": [1], "prob_win": [0.04959955408978719], "prob_eliminated": [0.054659648741160666], "eliminated_this_episode": [1], "win_features": {"age": [26], "num_previous_seasons": [0], "votes_against_last_3_eps": [0], "times_in_danger": [0], "final_n": [20.0], "confessional_share_rolling_3": [0.0], "elim_risk_rank": [7.5]}, "elim_features": {"age": [26], "mbti_feeling": [0], "num_previous_seasons": [0], "votes_against_last_3_eps": [0], "advantages_held": [0], "individual_immunity_wins": [0]}}, {"season": 36, "castaway_id": "US0518", "castaway": "Jacob", "won_season": 0, "episode": [1], "prob_win": [0.0631612099183707], "prob_eliminated": [0.024385040197775845], "eliminated_this_episode": [1], "win_features": {"age": [22], "num_previous_seasons": [0], "votes_against_last_3_eps": [0], "times_in_danger": [0], "final_n": [20.0], "confessional_share_rolling_3": [0.0], "elim_risk_rank": [20.0]}, "elim_features": {"age": [22], "mbti_feeling": [1], "num_previous_seasons": [0], "votes_against_last_3_eps": [0], "advantages_held": [1], "individual_immunity_wins": [0]}}, {"season": 36, "castaway_id": "US0519", "castaway": "Morgan", "won_season": 0, "episode": [1, 2], "prob_win": [0.053764852476424624, 0.06043112593679033], "prob_eliminated": [0.025010540727520097, 0.027370145970251593], "eliminated_this_episode": [0, 1], "win_features": {"age": [29, 29], "num_previous_seasons": [0, 0], "votes_against_last_3_eps": [0, 0], "times_in_danger": [0, 0], "final_n": [20.0, 18.0], "confessional_share_rolling_3": [0.0, 0.03389830508474576], "elim_risk_rank": [19.0, 17.0]}, "elim_features": {"age": [29, 29], "mbti_feeling": [1, 1], "num_previous_seasons": [0, 0], "votes_against_last_3_eps": [0, 0], "advantages_held": [1, 1], "individual_immunity_wins": [0, 0]}}, {"season": 36, "castaway_id": "US0520", "castaway": "Brendan", "won_season": 0, "episode": [1, 2, 3], "prob_win": [0.032628950570143644, 0.04071932143296673, 0.04785245589067687], "prob_eliminated": [0.05628542650981953, 0.06159564306726528, 0.060229834906337716], "eliminated_this_episode": [0, 0, 1], "win_features": {"age": [40, 40, 40], "num_previous_seasons": [0, 0, 0], "votes_against_last_3_eps": [0, 0, 0], "times_in_danger": [0, 0, 0], "final_n": [20.0, 18.0, 17.0], "confessional_share_rolling_3": [0.0, 0.03389830508474576, 0.04819915254237288], "elim_risk_rank": [2.0, 4.0, 5.0]}, "elim_features": {"age": [40, 40, 40], "mbti_feeling": [1, 1, 1], "num_previous_seasons": [0, 0, 0], "votes_against_last_3_eps": [0, 0, 0], "advantages_held": [0, 0, 0], "individual_immunity_wins": [0, 0, 0]}}, {"season": 36, "castaway_id": "US0521", "castaway": "Stephanie", "won_season": 0, "episode": [1, 2, 3, 4], "prob_win": [0.03909218533762972, 0.05973608186501692, 0.06582533921132838, 0.06569572655921682], "prob_eliminated": [0.05513668979984891, 0.06033852944561989, 0.05900059624399393, 0.05739382174184918], "eliminated_this_episode": [0, 0, 0, 1], "win_features": {"age": [34, 34, 34, 34], "num_previous_seasons": [0, 0, 0, 0], "votes_against_last_3_eps": [0, 0, 0, 0], "times_in_danger": [0, 0, 0, 0], "final_n": [20.0, 18.0, 17.0, 16.0], "confessional_share_rolling_3": [0.0, 0.0847457627118644, 0.0892478813559322, 0.07338747645951035], "elim_risk_rank": [4.0, 6.0, 7.0, 8.0]}, "elim_features": {"age": [34, 34, 34, 34], "mbti_feeling": [1, 1, 1, 1], "num_previous_seasons": [0, 0, 0, 0], "votes_against_last_3_eps": [0, 0, 0, 0], "advantages_held": [0, 0, 0, 0], "individual_immunity_wins": [0, 0, 0, 0]}}, {"season": 36, "castaway_id": "US0522", "castaway": "James", "won_season": 0, "episode": [1, 2, 3, 4, 5], "prob_win": [0.053578763217120774, 0.04172950481845323, 0.04896830196021314, 0.04888941845409062, 0.05658194692965701], "prob_eliminated": [0.054284451663189126, 0.08258086582660094, 0.08074973597932807, 0.07855066300233737, 0.06205592102270944], "eliminated_this_episode": [0, 0, 0, 0, 1], "win_features": {"age": [24, 24, 24, 24, 24], "num_previous_seasons": [0, 0, 0, 0, 0], "votes_against_last_3_eps": [0, 2, 2, 2, 0], "times_in_danger": [0, 1, 1, 1, 1], "final_n": [20.0, 18.0, 17.0, 16.0, 15.0], "confessional_share_rolling_3": [0.0, 0.03389830508474576, 0.04819915254237288, 0.032132768361581916, 0.03598484848484849], "elim_risk_rank": [10.0, 1.0, 2.0, 3.0, 9.0]}, "elim_features": {"age": [24, 24, 24, 24, 24], "mbti_feeling": [0, 0, 0, 0, 0], "num_previous_seasons": [0, 0, 0, 0, 0], "votes_against_last_3_eps": [0, 2, 2, 2, 0], "advantages_held": [0, 0, 0, 0, 0], "individual_immunity_wins": [0, 0, 0, 0, 0]}}, {"season": 36, "castaway_id": "US0523", "castaway": "Bradley", "won_season": 0, "episode": [1, 2, 3, 4, 5, 6], "prob_win": [0.04959955408978719, 0.05061045612882334, 0.05518964395593653, 0.04559977327650684, 0.06012246707179304, 0.07249203049487396], "prob_eliminated": [0.054659648741160666, 0.05981648221951839, 0.058490124777577576, 0.10836465410284299, 0.11900657710766561, 0.14896655884640414], "eliminated_this_episode": [0, 0, 0, 0, 0, 1], "win_features": {"age": [26, 26, 26, 26, 26, 26], "num_previous_seasons": [0, 0, 0, 0, 0, 0], "votes_against_last_3_eps": [0, 0, 0, 4, 4, 4], "times_in_danger": [0, 0, 0, 1, 1, 1], "final_n": [20.0, 18.0, 17.0, 16.0, 15.0, 14.0], "confessional_share_rolling_3": [0.0, 0.0, 0.0, 0.027777777777777776, 0.07323232323232322, 0.10656565656565657], "elim_risk_rank": [7.5, 9.0, 10.0, 1.0, 1.0, 1.0]}, "elim_features": {"age": [26, 26, 26, 26, 26, 26], "mbti_feeling": [0, 0, 0, 0, 0, 0], "num_previous_seasons": [0, 0, 0, 0, 0, 0], "votes_against_last_3_eps": [0, 0, 0, 4, 4, 4], "advantages_held": [0, 0, 0, 0, 0, 0], "individual_immunity_wins": [0, 0, 0, 0, 0, 0]}}, {"season": 36, "castaway_id": "US0524", "castaway": "Chris", "won_season": 0, "episode": [1, 2, 3, 4, 5, 6, 7], "prob_win": [0.047521286352364196, 0.05678874630283189, 0.06921793663886713, 0.07480906707947386, 0.08621452444960431, 0.08645285835605117, 0.09385902725278374], "prob_eliminated": [0.054848128110990914, 0.06002274356831675, 0.05869181253286439, 0.057093447196479054, 0.06270029450453406, 0.07848513366237223, 0.0440571503662387], "eliminated_this_episode": [0, 0, 0, 0, 0, 0, 1], "win_features": {"age": [27, 27, 27, 27, 27, 27, 27], "num_previous_seasons": [0, 0, 0, 0, 0, 0, 0], "votes_against_last_3_eps": [0, 0, 0, 0, 0, 0, 0], "times_in_danger": [0, 0, 0, 0, 0, 0, 0], "final_n": [20.0, 18.0, 17.0, 16.0, 15.0, 14.0, 13.0], "confessional_share_rolling_3": [0.0, 0.03389830508474576, 0.06382415254237288, 0.07032721280602637, 0.10448232323232325, 0.09545454545454546, 0.0791710205503309], "elim_risk_rank": [6.0, 8.0, 9.0, 10.0, 7.0, 5.0, 10.0]}, "elim_features": {"age": [27, 27, 27, 27, 27, 27, 27], "mbti_feeling": [0, 0, 0, 0, 0, 0, 0], "num_previous_seasons": [0, 0, 0, 0, 0, 0, 0], "votes_against_last_3_eps": [0, 0, 0, 0, 0, 0, 0], "advantages_held": [0, 0, 0, 0, 0, 0, 1], "individual_immunity_wins": [0, 0, 0, 0, 0, 0, 0]}}, {"season": 36, "castaway_id": "US0525", "castaway": "Libby", "won_season": 0, "episode": [1, 2, 3, 4, 5, 6, 7, 8], "prob_win": [0.05633439782369405, 0.05534682592744113, 0.05300077414987977, 0.051799115383655996, 0.05454803722546885, 0.05168772466727642, 0.04362683996102213, 0.03752566728271231], "prob_eliminated": [0.05326927985005717, 0.058294939766014915, 0.0673296907614953, 0.06549608843813107, 0.07192811496971724, 0.07622587484972448, 0.10945304438669735, 0.1455349512316566], "eliminated_this_episode": [0, 0, 0, 0, 0, 0, 0, 1], "win_features": {"age": [24, 24, 24, 24, 24, 24, 24, 24], "num_previous_seasons": [0, 0, 0, 0, 0, 0, 0, 0], "votes_against_last_3_eps": [0, 0, 1, 1, 1, 0, 1, 3], "times_in_danger": [0, 0, 1, 1, 1, 1, 2, 3], "final_n": [20.0, 18.0, 17.0, 16.0, 15.0, 14.0, 13.0, 12.0], "confessional_share_rolling_3": [0.0, 0.0, 0.0625, 0.041666666666666664, 0.041666666666666664, 0.0, 0.022988505747126436, 0.03251231527093596], "elim_risk_rank": [14.0, 13.0, 4.0, 5.0, 3.0, 9.0, 2.0, 1.0]}, "elim_features": {"age": [24, 24, 24, 24, 24, 24, 24, 24], "mbti_feeling": [1, 1, 1, 1, 1, 1, 1, 1], "num_previous_seasons": [0, 0, 0, 0, 0, 0, 0, 0], "votes_against_last_3_eps": [0, 0, 1, 1, 1, 0, 1, 3], "advantages_held": [0, 0, 0, 0, 0, 0, 0, 0], "individual_immunity_wins": [0, 0, 0, 0, 0, 0, 0, 0]}}, {"season": 36, "castaway_id": "US0526", "castaway": "Desiree", "won_season": 0, "episode": [1, 2, 3, 4, 5, 6, 7, 8, 9], "prob_win": [0.061504847491768454, 0.06430768622419843, 0.06652230709202817, 0.06900961304216954, 0.05230859834258228, 0.04985193568691485, 0.06090653393366938, 0.06720495570733431, 0.06406974133164228], "prob_eliminated": [0.05272037464584023, 0.05769424841244024, 0.056414948913379226, 0.05487858983865133, 0.07119895071289936, 0.10497948488557951, 0.12761913095148392, 0.10422473601359672, 0.08268482476424906], "eliminated_this_episode": [0, 0, 0, 0, 0, 0, 0, 0, 1], "win_features": {"age": [21, 21, 21, 21, 21, 21, 21, 21, 21], "num_previous_seasons": [0, 0, 0, 0, 0, 0, 0, 0, 0], "votes_against_last_3_eps": [0, 0, 0, 0, 1, 2, 2, 1, 0], "times_in_danger": [0, 0, 0, 0, 1, 2, 2, 2, 2], "final_n": [20.0, 18.0, 17.0, 16.0, 15.0, 14.0, 13.0, 12.0, 11.0], "confessional_share_rolling_3": [0.0, 0.01694915254237288, 0.00847457627118644, 0.005649717514124294, 0.015151515151515152, 0.05959595959595959, 0.08258446534308604, 0.07695675971538041, 0.03251231527093597], "elim_risk_rank": [16.0, 15.0, 15.0, 15.0, 4.0, 2.0, 1.0, 2.0, 7.0]}, "elim_features": {"age": [21, 21, 21, 21, 21, 21, 21, 21, 21], "mbti_feeling": [1, 1, 1, 1, 1, 1, 1, 1, 1], "num_previous_seasons": [0, 0, 0, 0, 0, 0, 0, 0, 0], "votes_against_last_3_eps": [0, 0, 0, 0, 1, 2, 2, 1, 0], "advantages_held": [0, 0, 0, 0, 0, 0, 0, 0, 0], "individual_immunity_wins": [0, 0, 0, 0, 0, 0, 0, 0, 0]}}, {"season": 36, "castaway_id": "US0527", "castaway": "Jenna", "won_season": 0, "episode": [1, 2, 3, 4, 5, 6, 7, 8, 9, 10], "prob_win": [0.05546179306643205, 0.06344772315180253, 0.06816787005895587, 0.06860242160181089, 0.07668983257601934, 0.07803480811565977, 0.08507943084575628, 0.08841388974906271, 0.0994602524893608, 0.10814542441636701], "prob_eliminated": [0.05409773111455626, 0.0592015507939656, 0.057888828705397334, 0.05631233118089432, 0.061842469191397395, 0.0774113502791757, 0.09410571274165552, 0.09052823056189542, 0.08484502334058212, 0.08047893976668122], "eliminated_this_episode": [0, 0, 0, 0, 0, 0, 0, 0, 0, 1], "win_features": {"age": [23, 23, 23, 23, 23, 23, 23, 23, 23, 23], "num_previous_seasons": [0, 0, 0, 0, 0, 0, 0, 0, 0, 0], "votes_against_last_3_eps": [0, 0, 0, 0, 0, 0, 0, 0, 0, 0], "times_in_danger": [0, 0, 0, 0, 0, 0, 0, 0, 0, 0], "final_n": [20.0, 18.0, 17.0, 16.0, 15.0, 14.0, 13.0, 12.0, 11.0, 10.0], "confessional_share_rolling_3": [0.0, 0.03389830508474576, 0.03257415254237288, 0.021716101694915252, 0.04071969696969697, 0.04141414141414141, 0.04141414141414141, 0.020634920634920634, 0.0373015873015873, 0.0373015873015873], "elim_risk_rank": [11.0, 11.0, 12.0, 12.0, 10.0, 6.0, 5.0, 5.0, 4.0, 5.0]}, "elim_features": {"age": [23, 23, 23, 23, 23, 23, 23, 23, 23, 23], "mbti_feeling": [0, 0, 0, 0, 0, 0, 0, 0, 0, 0], "num_previous_seasons": [0, 0, 0, 0, 0, 0, 0, 0, 0, 0], "votes_against_last_3_eps": [0, 0, 0, 0, 0, 0, 0, 0, 0, 0], "advantages_held": [0, 0, 0, 0, 0, 0, 0, 0, 0, 0], "individual_immunity_wins": [0, 0, 0, 0, 0, 0, 0, 0, 0, 0]}}, {"season": 36, "castaway_id": "US0528", "castaway": "Michael", "won_season": 0, "episode": [1, 2, 3, 4, 5, 6, 7, 8, 9, 10], "prob_win": [0.06613337453501189, 0.06502772274370729, 0.06476171078662082, 0.0639362147096726, 0.083370702999377, 0.09251745209149866, 0.10766626977445659, 0.1068771913076325, 0.0927161292837527, 0.0787065383452907], "prob_eliminated": [0.052176625057461526, 0.03134872541609145, 0.030653605714829172, 0.064174183394431, 0.05964633379529904, 0.034392094497909795, 0.041809018364001, 0.04021962475767354, 0.243293050560048, 0.3007044000901444], "eliminated_this_episode": [0, 0, 0, 0, 0, 0, 0, 0, 0, 1], "win_features": {"age": [18, 18, 18, 18, 18, 18, 18, 18, 18, 18], "num_previous_seasons": [0, 0, 0, 0, 0, 0, 0, 0, 0, 0], "votes_against_last_3_eps": [0, 1, 1, 1, 0, 0, 0, 0, 7, 9], "times_in_danger": [0, 1, 1, 1, 1, 1, 1, 1, 2, 3], "final_n": [20.0, 18.0, 17.0, 16.0, 15.0, 14.0, 13.0, 12.0, 11.0, 10.0], "confessional_share_rolling_3": [0.0, 0.06779661016949153, 0.04952330508474576, 0.060793314500941616, 0.09880050505050504, 0.12171717171717171, 0.15141065830721004, 0.10985221674876848, 0.11818555008210181, 0.11009700176366843], "elim_risk_rank": [17.0, 16.0, 16.0, 6.0, 14.0, 13.0, 12.0, 12.0, 1.0, 1.0]}, "elim_features": {"age": [18, 18, 18, 18, 18, 18, 18, 18, 18, 18], "mbti_feeling": [1, 1, 1, 1, 1, 1, 1, 1, 1, 1], "num_previous_seasons": [0, 0, 0, 0, 0, 0, 0, 0, 0, 0], "votes_against_last_3_eps": [0, 1, 1, 1, 0, 0, 0, 0, 7, 9], "advantages_held": [0, 1, 1, 0, 0, 1, 1, 1, 0, 0], "individual_immunity_wins": [0, 0, 0, 0, 0, 0, 0, 0, 0, 0]}}, {"season": 36, "castaway_id": "US0529", "castaway": "Chelsea", "won_season": 0, "episode": [1, 2, 3, 4, 5, 6, 7, 8, 9, 10, 11], "prob_win": [0.05409282235533955, 0.053587437864184156, 0.05830160949634156, 0.06490260321411309, 0.06832848334339083, 0.07234209236599606, 0.07845230615353885, 0.0874149969920165, 0.08979223454673779, 0.09220567024057154, 0.12390304320582665], "prob_eliminated": [0.053453400545113154, 0.05849643122334599, 0.057199344300124244, 0.055641623636069185, 0.06110589498451464, 0.07648934304561687, 0.09298486744501488, 0.08944999483653562, 0.08383447740682223, 0.1394787214946312, 0.2519686057214246], "eliminated_this_episode": [0, 0, 0, 0, 0, 0, 0, 0, 0, 0, 1], "win_features": {"age": [25, 25, 25, 25, 25, 25, 25, 25, 25, 25, 25], "num_previous_seasons": [0, 0, 0, 0, 0, 0, 0, 0, 0, 0, 0], "votes_against_last_3_eps": [0, 0, 0, 0, 0, 0, 0, 0, 0, 0, 0], "times_in_danger": [0, 0, 0, 0, 0, 0, 0, 0, 0, 0, 0], "final_n": [20.0, 18.0, 17.0, 16.0, 15.0, 14.0, 13.0, 12.0, 11.0, 10.0, 8.0], "confessional_share_rolling_3": [0.0, 0.0, 0.0, 0.013888888888888888, 0.013888888888888888, 0.024999999999999998, 0.02260536398467433, 0.02260536398467433, 0.011494252873563218, 0.0, 0.0], "elim_risk_rank": [12.5, 12.0, 13.0, 13.0, 11.5, 7.5, 6.5, 6.5, 5.0, 3.0, 1.0]}, "elim_features": {"age": [25, 25, 25, 25, 25, 25, 25, 25, 25, 25, 25], "mbti_feeling": [1, 1, 1, 1, 1, 1, 1, 1, 1, 1, 1], "num_previous_seasons": [0, 0, 0, 0, 0, 0, 0, 0, 0, 0, 0], "votes_against_last_3_eps": [0, 0, 0, 0, 0, 0, 0, 0, 0, 0, 0], "advantages_held": [0, 0, 0, 0, 0, 0, 0, 0, 0, 0, 0], "individual_immunity_wins": [0, 0, 0, 0, 0, 0, 0, 0, 0, 1, 2]}}, {"season": 36, "castaway_id": "US0530", "castaway": "Kellyn", "won_season": 0, "episode": [1, 2, 3, 4, 5, 6, 7, 8, 9, 10, 11, 12], "prob_win": [0.04612212433276589, 0.054693407352932315, 0.06300546586857708, 0.07990328950166416, 0.08347299998635156, 0.09342160606716063, 0.0948664485986981, 0.10686572893525408, 0.10781202501367874, 0.11600472184402039, 0.1411534920484756, 0.19215802177696914], "prob_eliminated": [0.05438270997593258, 0.05951341582396567, 0.058193778509224386, 0.05660897622849151, 0.062168246189651624, 0.03591857777999318, 0.043664699691488736, 0.0764488158572409, 0.07164949017017067, 0.06796244230580017, 0.17900401964567977, 0.2304082993346687], "eliminated_this_episode": [0, 0, 0, 0, 0, 0, 0, 0, 0, 0, 0, 1], "win_features": {"age": [30, 30, 30, 30, 30, 30, 30, 30, 30, 30, 30, 30], "num_previous_seasons": [0, 0, 0, 0, 0, 0, 0, 0, 0, 0, 0, 0], "votes_against_last_3_eps": [0, 0, 0, 0, 0, 0, 0, 0, 0, 0, 1, 1], "times_in_danger": [0, 0, 0, 0, 0, 0, 0, 0, 0, 0, 1, 1], "final_n": [20.0, 18.0, 17.0, 16.0, 15.0, 14.0, 13.0, 12.0, 11.0, 10.0, 8.0, 7.0], "confessional_share_rolling_3": [0.0, 0.03389830508474576, 0.04819915254237288, 0.10157721280602637, 0.10542929292929293, 0.11792929292929293, 0.09446185997910135, 0.10788177339901477, 0.08843732895457034, 0.09184303350970018, 0.13223712217965092, 0.2294593444018731], "elim_risk_rank": [9.0, 10.0, 11.0, 11.0, 8.0, 12.0, 11.0, 9.0, 8.0, 7.0, 2.0, 1.0]}, "elim_features": {"age": [30, 30, 30, 30, 30, 30, 30, 30, 30, 30, 30, 30], "mbti_feeling": [1, 1, 1, 1, 1, 1, 1, 1, 1, 1, 1, 1], "num_previous_seasons": [0, 0, 0, 0, 0, 0, 0, 0, 0, 0, 0, 0], "votes_against_last_3_eps": [0, 0, 0, 0, 0, 0, 0, 0, 0, 0, 1, 1], "advantages_held": [0, 0, 0, 0, 0, 1, 1, 1, 1, 1, 0, 0], "individual_immunity_wins": [0, 0, 0, 0, 0, 0, 0, 1, 1, 1, 1, 1]}}, {"season": 36, "castaway_id": "US0531", "castaway": "Sebastian", "won_season": 0, "episode": [1, 2, 3, 4, 5, 6, 7, 8, 9, 10, 11, 12, 13], "prob_win": [0.05951630016440774, 0.06244179266275067, 0.06860848929648578, 0.07332895954105209, 0.07972991735038944, 0.08178840552534047, 0.08446740949337242, 0.08939591016635437, 0.09142351617465364, 0.10286826357278087, 0.11780547335939473, 0.1368271477217192, 0.18366929502200943], "prob_eliminated": [0.052902768315735337, 0.057893849909403716, 0.0566101244909122, 0.05506845016241763, 0.06047643315719734, 0.07570141380153994, 0.09202701510376977, 0.0885285557966918, 0.0829708847312864, 0.07870124341734472, 0.10068969374565119, 0.06026817605902947, 0.06206143067345948], "eliminated_this_episode": [0, 0, 0, 0, 0, 0, 0, 0, 0, 0, 0, 0, 1], "win_features": {"age": [22, 22, 22, 22, 22, 22, 22, 22, 22, 22, 22, 22, 22], "num_previous_seasons": [0, 0, 0, 0, 0, 0, 0, 0, 0, 0, 0, 0, 0], "votes_against_last_3_eps": [0, 0, 0, 0, 0, 0, 0, 0, 0, 0, 1, 1, 1], "times_in_danger": [0, 0, 0, 0, 0, 0, 0, 0, 0, 0, 1, 1, 1], "final_n": [20.0, 18.0, 17.0, 16.0, 15.0, 14.0, 13.0, 12.0, 11.0, 10.0, 8.0, 7.0, 6.0], "confessional_share_rolling_3": [0.0, 0.01694915254237288, 0.02409957627118644, 0.02995527306967985, 0.03945707070707071, 0.04015151515151515, 0.026262626262626265, 0.011111111111111113, 0.0, 0.01234567901234568, 0.0238399318859089, 0.0238399318859089, 0.05149425287356322], "elim_risk_rank": [15.0, 14.0, 14.0, 14.0, 13.0, 10.0, 8.0, 8.0, 6.0, 6.0, 5.0, 7.0, 6.0]}, "elim_features": {"age": [22, 22, 22, 22, 22, 22, 22, 22, 22, 22, 22, 22, 22], "mbti_feeling": [1, 1, 1, 1, 1, 1, 1, 1, 1, 1, 1, 1, 1], "num_previous_seasons": [0, 0, 0, 0, 0, 0, 0, 0, 0, 0, 0, 0, 0], "votes_against_last_3_eps": [0, 0, 0, 0, 0, 0, 0, 0, 0, 0, 1, 1, 1], "advantages_held": [0, 0, 0, 0, 0, 0, 0, 0, 0, 0, 0, 1, 1], "individual_immunity_wins": [0, 0, 0, 0, 0, 0, 0, 0, 0, 0, 0, 0, 0]}}, {"season": 36, "castaway_id": "US0532", "castaway": "Donathan", "won_season": 0, "episode": [1, 2, 3, 4, 5, 6, 7, 8, 9, 10, 11, 12, 13], "prob_win": [0.05409282235533955, 0.05583651983156709, 0.05218674934011353, 0.053904133671803446, 0.06546457757150123, 0.06394168238444888, 0.07579299480426076, 0.07157585942117259, 0.08565821740409324, 0.08929406169890709, 0.11304034513596933, 0.1367491513258474, 0.17379451392007778], "prob_eliminated": [0.053453400545113154, 0.06909058750388107, 0.06755858810332233, 0.06571875217494612, 0.06110589498451464, 0.07648934304561687, 0.09298486744501488, 0.08944999483653562, 0.017372558174661348, 0.016478574793001445, 0.04732954747424051, 0.06092109307603703, 0.12431391620485896], "eliminated_this_episode": [0, 0, 0, 0, 0, 0, 0, 0, 0, 0, 0, 0, 1], "win_features": {"age": [25, 25, 25, 25, 25, 25, 25, 25, 25, 25, 25, 25, 25], "num_previous_seasons": [0, 0, 0, 0, 0, 0, 0, 0, 0, 0, 0, 0, 0], "votes_against_last_3_eps": [0, 1, 1, 1, 0, 0, 0, 0, 0, 0, 1, 1, 5], "times_in_danger": [0, 1, 1, 1, 1, 1, 1, 1, 1, 1, 2, 2, 3], "final_n": [20.0, 18.0, 17.0, 16.0, 15.0, 14.0, 13.0, 12.0, 11.0, 10.0, 8.0, 7.0, 6.0], "confessional_share_rolling_3": [0.0, 0.1016949152542373, 0.06647245762711865, 0.058203860640301315, 0.06976010101010101, 0.05934343434343434, 0.0799373040752351, 0.034482758620689655, 0.04837164750957854, 0.038580246913580245, 0.08455725840783312, 0.10770540655598126, 0.17634738186462326], "elim_risk_rank": [12.5, 2.0, 3.0, 4.0, 11.5, 7.5, 6.5, 6.5, 11.0, 10.0, 8.0, 6.0, 4.0]}, "elim_features": {"age": [25, 25, 25, 25, 25, 25, 25, 25, 25, 25, 25, 25, 25], "mbti_feeling": [1, 1, 1, 1, 1, 1, 1, 1, 1, 1, 1, 1, 1], "num_previous_seasons": [0, 0, 0, 0, 0, 0, 0, 0, 0, 0, 0, 0, 0], "votes_against_last_3_eps": [0, 1, 1, 1, 0, 0, 0, 0, 0, 0, 1, 1, 5], "advantages_held": [0, 0, 0, 0, 0, 0, 0, 0, 2, 2, 1, 1, 1], "individual_immunity_wins": [0, 0, 0, 0, 0, 0, 0, 0, 0, 0, 0, 0, 0]}}, {"season": 36, "castaway_id": "US0533", "castaway": "Angela", "won_season": 0, "episode": [1, 2, 3, 4, 5, 6, 7, 8, 9, 10, 11, 12, 13], "prob_win": [0.03051429804612783, 0.032179790258937795, 0.03444926632708956, 0.03608380314654754, 0.03930503917142042, 0.037772588112691755, 0.03977538463682182, 0.045385369268460096, 0.050858631357746695, 0.0665101659036657, 0.09445174089749198, 0.09669326405176878, 0.1057664414959238], "prob_eliminated": [0.057746809403714794, 0.06319489929927191, 0.10040328464547207, 0.09766898282532141, 0.10726054018128353, 0.0826330124786497, 0.10045346718858768, 0.09663467151410134, 0.1579887667682257, 0.14985874178516134, 0.16230149302092886, 0.20890933656378569, 0.2151253473390843], "eliminated_this_episode": [0, 0, 0, 0, 0, 0, 0, 0, 0, 0, 0, 0, 1], "win_features": {"age": [42, 42, 42, 42, 42, 42, 42, 42, 42, 42, 42, 42, 42], "num_previous_seasons": [0, 0, 0, 0, 0, 0, 0, 0, 0, 0, 0, 0, 0], "votes_against_last_3_eps": [0, 0, 3, 3, 3, 0, 0, 0, 0, 0, 0, 0, 0], "times_in_danger": [0, 0, 1, 1, 1, 1, 1, 1, 1, 1, 1, 1, 1], "final_n": [20.0, 18.0, 17.0, 16.0, 15.0, 14.0, 13.0, 12.0, 11.0, 10.0, 8.0, 7.0, 6.0], "confessional_share_rolling_3": [0.0, 0.0, 0.0625, 0.05555555555555555, 0.05555555555555555, 0.036111111111111115, 0.022222222222222227, 0.022222222222222227, 0.027777777777777776, 0.06481481481481481, 0.06481481481481481, 0.037037037037037035, 0.0], "elim_risk_rank": [1.0, 3.0, 1.0, 2.0, 2.0, 3.0, 3.0, 3.0, 2.0, 2.0, 3.0, 2.0, 2.0]}, "elim_features": {"age": [42, 42, 42, 42, 42, 42, 42, 42, 42, 42, 42, 42, 42], "mbti_feeling": [0, 0, 0, 0, 0, 0, 0, 0, 0, 0, 0, 0, 0], "num_previous_seasons": [0, 0, 0, 0, 0, 0, 0, 0, 0, 0, 0, 0, 0], "votes_against_last_3_eps": [0, 0, 3, 3, 3, 0, 0, 0, 0, 0, 0, 0, 0], "advantages_held": [0, 0, 0, 0, 0, 0, 0, 0, 0, 0, 0, 0, 0], "individual_immunity_wins": [0, 0, 0, 0, 0, 0, 0, 0, 1, 1, 1, 1, 1]}}, {"season": 36, "castaway_id": "US0534", "castaway": "Laurel", "won_season": 0, "episode": [1, 2, 3, 4, 5, 6, 7, 8, 9, 10, 11, 12, 13], "prob_win": [0.04353452671999569, 0.04876866105436389, 0.05129120896713073, 0.057580368719193274, 0.05909984299341681, 0.0707086203701967, 0.07434770522450483, 0.08580658656636524, 0.09433376019742824, 0.11752875942956495, 0.13901382543386995, 0.16269757572006013, 0.19410124134535398], "prob_eliminated": [0.05522685561775456, 0.06043720190634319, 0.05909708076340509, 0.057487678679922, 0.06313324138948509, 0.07902707520192324, 0.09606988136681535, 0.09241773019991475, 0.08661590342842569, 0.08215869122778323, 0.12361544237255391, 0.1591138785874203, 0.27908269050453616], "eliminated_this_episode": [0, 0, 0, 0, 0, 0, 0, 0, 0, 0, 0, 0, 0], "win_features": {"age": [29, 29, 29, 29, 29, 29, 29, 29, 29, 29, 29, 29, 29], "num_previous_seasons": [0, 0, 0, 0, 0, 0, 0, 0, 0, 0, 0, 0, 0], "votes_against_last_3_eps": [0, 0, 0, 0, 0, 0, 0, 0, 0, 0, 2, 2, 2], "times_in_danger": [0, 0, 0, 0, 0, 0, 0, 0, 0, 0, 1, 1, 1], "final_n": [20.0, 18.0, 17.0, 16.0, 15.0, 14.0, 13.0, 12.0, 11.0, 10.0, 8.0, 7.0, 6.0], "confessional_share_rolling_3": [0.0, 0.01694915254237288, 0.00847457627118644, 0.019538606403013182, 0.013888888888888888, 0.04722222222222222, 0.03333333333333333, 0.042857142857142864, 0.051190476190476196, 0.1005731922398589, 0.11403788846317582, 0.1279267773520647, 0.11854406130268198], "elim_risk_rank": [3.0, 5.0, 6.0, 7.0, 5.0, 4.0, 4.0, 4.0, 3.0, 4.0, 4.0, 4.0, 1.0]}, "elim_features": {"age": [29, 29, 29, 29, 29, 29, 29, 29, 29, 29, 29, 29, 29], "mbti_feeling": [0, 0, 0, 0, 0, 0, 0, 0, 0, 0, 0, 0, 0], "num_previous_seasons": [0, 0, 0, 0, 0, 0, 0, 0, 0, 0, 0, 0, 0], "votes_against_last_3_eps": [0, 0, 0, 0, 0, 0, 0, 0, 0, 0, 2, 2, 2], "advantages_held": [0, 0, 0, 0, 0, 0, 0, 0, 0, 0, 0, 0, 0], "individual_immunity_wins": [0, 0, 0, 0, 0, 0, 0, 0, 0, 0, 0, 0, 1]}}, {"season": 36, "castaway_id": "US0535", "castaway": "Domenick", "won_season": 0, "episode": [1, 2, 3, 4, 5, 6, 7, 8, 9, 10, 11, 12, 13], "prob_win": [0.043113979957328574, 0.08481904078159672, 0.07890797219817007, 0.08436581336706733, 0.07368129796874191, 0.08041653891164906, 0.08180791650015388, 0.1126639355585634, 0.11535398271056171, 0.126680566953967, 0.15523011439425705, 0.17488452977409613, 0.19555983658551773], "prob_eliminated": [0.026353158964276285, 0.01297845551951205, 0.01269067411839205, 0.012345066567171135, 0.013557410656532265, 0.016970497441868623, 0.020630317796912278, 0.044099905885153744, 0.04133138934583639, 0.039204496182227044, 0.07714849617921592, 0.17542746678479768, 0.2113420698476016], "eliminated_this_episode": [0, 0, 0, 0, 0, 0, 0, 0, 0, 0, 0, 0, 0], "win_features": {"age": [38, 38, 38, 38, 38, 38, 38, 38, 38, 38, 38, 38, 38], "num_previous_seasons": [0, 0, 0, 0, 0, 0, 0, 0, 0, 0, 0, 0, 0], "votes_against_last_3_eps": [0, 0, 0, 0, 0, 0, 0, 0, 0, 0, 0, 0, 1], "times_in_danger": [0, 0, 0, 0, 0, 0, 0, 0, 0, 0, 0, 0, 1], "final_n": [20.0, 18.0, 17.0, 16.0, 15.0, 14.0, 13.0, 12.0, 11.0, 10.0, 8.0, 7.0, 6.0], "confessional_share_rolling_3": [0.0, 0.1694915254237288, 0.1316207627118644, 0.14330273069679847, 0.08680555555555554, 0.09999999999999999, 0.07892720306513411, 0.1646414887794198, 0.14797482211275312, 0.1628747795414462, 0.13463175819497658, 0.14389101745423585, 0.1611749680715198], "elim_risk_rank": [18.0, 18.0, 17.0, 16.0, 15.0, 14.0, 13.0, 10.0, 10.0, 9.0, 6.0, 3.0, 3.0]}, "elim_features": {"age": [38, 38, 38, 38, 38, 38, 38, 38, 38, 38, 38, 38, 38], "mbti_feeling": [0, 0, 0, 0, 0, 0, 0, 0, 0, 0, 0, 0, 0], "num_previous_seasons": [0, 0, 0, 0, 0, 0, 0, 0, 0, 0, 0, 0, 0], "votes_against_last_3_eps": [0, 0, 0, 0, 0, 0, 0, 0, 0, 0, 0, 0, 1], "advantages_held": [1, 2, 2, 2, 2, 2, 2, 1, 1, 1, 1, 1, 1], "individual_immunity_wins": [0, 0, 0, 0, 0, 0, 0, 0, 0, 0, 1, 2, 2]}}, {"season": 36, "castaway_id": "US0536", "castaway": "Wendell", "won_season": 1, "episode": [1, 2, 3, 4, 5, 6, 7, 8, 9, 10, 11, 12, 13], "prob_win": [0.040632357100160776, 0.04952815566163555, 0.05374289876158505, 0.061589678731961923, 0.061081732020286, 0.06857165685024165, 0.07935173282096122, 0.10086990904507191, 0.1085215094903441, 0.1020558275948648, 0.11540196552471466, 0.09999030962953914, 0.14710867163111727], "prob_eliminated": [0.05494731147297922, 0.06013128432819138, 0.05879794653394492, 0.057196690830044625, 0.06281367715259877, 0.03631024018362561, 0.04414082715231995, 0.04246278850900392, 0.047413631309692394, 0.04497374893722534, 0.057942701840305186, 0.10495174959426119, 0.10807454543045963], "eliminated_this_episode": [0, 0, 0, 0, 0, 0, 0, 0, 0, 0, 0, 0, 0], "win_features": {"age": [33, 33, 33, 33, 33, 33, 33, 33, 33, 33, 33, 33, 33], "num_previous_seasons": [0, 0, 0, 0, 0, 0, 0, 0, 0, 0, 0, 0, 0], "votes_against_last_3_eps": [0, 0, 0, 0, 0, 0, 0, 0, 1, 1, 2, 4, 4], "times_in_danger": [0, 0, 0, 0, 0, 0, 0, 0, 1, 1, 2, 3, 3], "final_n": [20.0, 18.0, 17.0, 16.0, 15.0, 14.0, 13.0, 12.0, 11.0, 10.0, 8.0, 7.0, 6.0], "confessional_share_rolling_3": [0.0, 0.03389830508474576, 0.03257415254237288, 0.049493879472693035, 0.03819444444444445, 0.03888888888888889, 0.05708812260536398, 0.09518336070060207, 0.1674055829228243, 0.12142857142857143, 0.12931034482758622, 0.12005108556832694, 0.16005108556832695], "elim_risk_rank": [5.0, 7.0, 8.0, 9.0, 6.0, 11.0, 9.0, 11.0, 9.0, 8.0, 7.0, 5.0, 5.0]}, "elim_features": {"age": [33, 33, 33, 33, 33, 33, 33, 33, 33, 33, 33, 33, 33], "mbti_feeling": [1, 1, 1, 1, 1, 1, 1, 1, 1, 1, 1, 1, 1], "num_previous_seasons": [0, 0, 0, 0, 0, 0, 0, 0, 0, 0, 0, 0, 0], "votes_against_last_3_eps": [0, 0, 0, 0, 0, 0, 0, 0, 1, 1, 2, 4, 4], "advantages_held": [0, 0, 0, 0, 0, 1, 1, 1, 1, 1, 1, 1, 1], "individual_immunity_wins": [0, 0, 0, 0, 0, 0, 0, 0, 0, 0, 0, 0, 0]}}]}